[
    {
        "featureType": "landscape",
        "elementType": "all",
        "stylers": [
            {
                "visibility": "on"
            }
        ]
    },
    {
        "featureType": "landscape",
        "elementType": "geometry",
        "stylers": [
            {
                "visibility": "on"
            },
            {
                "color": "#f3f3f3"
            }
        ]
    },
    {
        "featureType": "poi",
        "elementType": "labels",
        "stylers": [
            {
                "visibility": "on"
            }
        ]
    },
    {
        "featureType": "poi.park",
        "elementType": "geometry",
        "stylers": [
            {
                "visibility": "on"
            },
            {
                "color": "#cdeacf"
            }
        ]
    },
    {
        "featureType": "road",
        "elementType": "geometry.stroke",
        "stylers": [
            {
                "color": "#b8cddd"
            }
        ]
    },
    {
        "featureType": "road.highway",
        "elementType": "geometry",
        "stylers": [
            {
                "color": "#dfdfdf"
            }
        ]
    },
    {
        "featureType": "road.highway",
        "elementType": "labels",
        "stylers": [
            {
                "visibility": "ON"
            }
        ]
    },
    {
        "featureType": "road.arterial",
        "elementType": "all",
        "stylers": [
            {
                "visibility": "on"
            }
        ]
    },
    {
        "featureType": "road.local",
        "elementType": "all",
        "stylers": [
            {
                "visibility": "on"
            }
        ]
    },
    {
        "featureType": "transit",
        "elementType": "all",
        "stylers": [
            {
                "visibility": "ON"
            }
        ]
    },
    {
        "featureType": "transit.line",
        "elementType": "geometry.stroke",
        "stylers": [
            {
                "color": "#f6cae6"
            }
        ]
    },
    {
        "featureType": "water",
        "elementType": "geometry",
        "stylers": [
            {
                "visibility": "on"
            },
            {
                "color": "#d3edff"
            }
        ]
    }
]
